crashlens/__init__.py
crashlens/__main__.py
crashlens/cli.py
crashlens/config/__init__.py
crashlens/config/config_schema.json
crashlens/config/crashlens-policy.yaml
crashlens/config/loader.py
crashlens/config/metrics_config.py
crashlens/config/modern-policy.yaml
crashlens/config/policy-schema.json
crashlens/config/pricing.yaml
crashlens/config/smtp_config.py
crashlens/config/variables.py
crashlens/detectors/__init__.py
crashlens/detectors/detectors.md
crashlens/detectors/driver.py
crashlens/detectors/fallback_failure.py
crashlens/detectors/fallback_storm.py
crashlens/detectors/overkill_model_detector.py
crashlens/detectors/retry_loops.py
crashlens/docs/working-commands-summary
crashlens/formatters/__init__.py
crashlens/formatters/error_formatter.py
crashlens/formatters/json_formatter.py
crashlens/formatters/markdown_formatter.py
crashlens/formatters/policy_report_json.py
crashlens/formatters/policy_report_markdown.py
crashlens/formatters/README.md
crashlens/formatters/schema.json
crashlens/formatters/schema_validator.py
crashlens/formatters/slack_formatter.py
crashlens/formatters/summary_formatter.py
crashlens/guard.py
crashlens/guard_adapter.py
crashlens/helicone_client.py
crashlens/io/__init__.py
crashlens/io/ingest.py
crashlens/io/stream_reader.py
crashlens/langfuse_client.py
crashlens/metrics.py
crashlens/observability/__init__.py
crashlens/observability/http_server.py
crashlens/observability/metrics.py
crashlens/observability/server.py
crashlens/openai_client.py
crashlens/parsers/__init__.py
crashlens/parsers/langfuse.py
crashlens/performance_baseline.py
crashlens/pii/__init__.py
crashlens/pii/patterns.py
crashlens/pii/remover.py
crashlens/pii/sanitizer.py
crashlens/policy/__init__.py
crashlens/policy/engine.py
crashlens/policy/templates/broken-templates/batch-processing-efficiency.yaml
crashlens/policy/templates/broken-templates/budget-protection.yaml
crashlens/policy/templates/broken-templates/chain-recursion-prevention.yaml
crashlens-2.10.1.dist-info/entry_points.txt
crashlens-2.10.1.dist-info/LICENSE
crashlens-2.10.1.dist-info/METADATA
crashlens-2.10.1.dist-info/WHEEL
crashlens-2.10.1.dist-info/RECORD
