Metadata-Version: 2.1
Name: crashlens
Version: 2.10.1
Summary: CLI to detect GPT token waste from Langfuse logs with automated CI/CD setup and Prometheus observability
License: MIT
Author: Aditya Singh
Author-email: coding103856@gmail.com
Requires-Python: >=3.12,<4.0
Classifier: License :: OSI Approved :: MIT License
Classifier: Programming Language :: Python :: 3
Classifier: Programming Language :: Python :: 3.12
Provides-Extra: metrics
Requires-Dist: click (>=8.2.1,<9.0.0)
Requires-Dist: faker (>=25.2.0,<26.0.0)
Requires-Dist: jinja2 (>=3.1.6,<4.0.0)
Requires-Dist: jsonschema (>=4.0.0,<5.0.0)
Requires-Dist: orjson (>=3.10.18,<4.0.0)
Requires-Dist: prometheus-client (>=0.20.0,<0.21.0) ; extra == "metrics"
Requires-Dist: pydantic (>=2.12.3,<3.0.0)
Requires-Dist: pyperclip (>=1.8.2,<2.0.0)
Requires-Dist: pyyaml (>=6.0.2,<7.0.0)
Requires-Dist: requests (>=2.31.0,<3.0.0)
Requires-Dist: rich (>=14.0.0,<15.0.0)
